{"name":"Раздолье","type":"КП","point":[36.671067,56.670206],"site":"","car":{"distance":160,"time":{"h":1,"m":49}},"developer":"","class":"","price":{"from":"","to":""},"address":{"name":""},"description":"Коттеджный посёлок «Раздолье» расположен в 118 км от центра Москвы, в северо-западном направлении. Коттеджный посёлок «Раздолье» расположен в районе с хорошей экологией. На машине, без учета пробок, до поселка можно добраться за 1 час 49 мин.","readyDate":"","id":2936,"props":{"energy":"","water":"","drainage":"","gas":"","scurity":""},"nature":{"forest":"","water":""},"eco":{"closestId":225,"closest":{"point":[37.1400118,56.7741571],"type":5,"name":"Поле аэрации","address":"Дубна","description":"","id":225},"distance":30.86},"railroad":{"closestId":3081,"closest":{"id":3081,"name":"Донховка","time":{"h":2,"m":34},"distance":128.28,"count":32,"nextId":[3091],"prevId":[3071],"point":[36.720721,56.627772],"route":"Ленинградское направление","path":{"id":303,"points":[[36.67309284210205,56.57598616495252],[36.720721,56.627772]],"time":{"hours":0,"min":4},"distance":6.45},"type":"платформа"},"distance":5.61},"moscow":{"distance":117.78},"city":{"closestId":17,"closest":{"id":17,"point":[37.1672,56.7325],"name":"Дубна"},"distance":31.07},"medic":{"closestId":10937,"closest":{"id":"10937","name":"Дубненская станция скорой медицинской помощи","point":[37.143307,56.75564],"address":"141983, Московская область, г. Дубна, ул. Карла Маркса, д.30","city":"Балашиха"},"distance":30.34},"markets":{"closestId":11788,"closest":{"id":11788,"name":"Азбука Вкуса","point":[37.520913,56.352547],"address":"Московская область, Дмитровский городской округ, Дмитров, Профессиональная улица, 7"},"distance":62.98},"title":"КП Раздолье в 117.78 км от Москвы, вблизи города Дубна."}