{"name":"Педагог","type":"СНТ","point":[37.777402,55.493579],"site":"","car":{"distance":35,"time":{"h":0,"m":42}},"developer":"","class":"","price":{"from":"","to":""},"address":{"name":""},"description":"Дачный посёлок «Педагог» расположен в 30 км от центра Москвы, в юго-восточном направлении. В 6 км от поселка находится город Домодедово. Дачный посёлок расположен в экологически чистом районе подмосковья. На машине, без учета пробок, до поселка можно добраться за 42 мин. В пешой доступности находится ж/д станция пригородной электички Ленинская (Павелецкое направление). На электричке до Москвы 13 остановок, время в пути 46 мин. Поезд прибывает на Павелецкий вокзал. Благодоря хорошей транспортной доступности поселок подойдет людям планирующим проживать в пригороде и работать в Москве.","readyDate":"","id":2638,"props":{"energy":"","water":"","drainage":"","gas":"","scurity":""},"nature":{"forest":"","water":""},"eco":{"closestId":290,"closest":{"point":[37.779,55.460244],"type":7,"name":"Полигон ТБО Домодедово","address":"Домодедовский район","description":"Закрыт до 2009 г.","id":290},"distance":3.71},"railroad":{"closestId":3671,"closest":{"id":3671,"name":"Ленинская","time":{"h":0,"m":46},"distance":28.85,"count":13,"nextId":[3681],"prevId":[3661],"point":[37.7309754,55.489095],"route":"Павелецкое направление","path":{"id":360,"points":[[37.7082629,55.516338],[37.72275924682617,55.50384707997055],[37.72842407226562,55.496846576284355],[37.72808074951172,55.492276131658016],[37.7309754,55.489095]],"time":{"hours":0,"min":3},"distance":3.42},"type":"платформа"},"distance":2.97},"moscow":{"distance":30.34},"city":{"closestId":15,"closest":{"id":15,"point":[37.7666,55.4364],"name":"Домодедово"},"distance":6.39},"medic":{"closestId":10951,"closest":{"id":"10951","name":"Отделение скорой медицинской помощи Подольской РБ Федюково","point":[37.685359,55.513632],"address":"143152, Московская область, Подольск, д.Федюково, ул. Строителей, д.14","city":"Балашиха"},"distance":6.21},"markets":{"closestId":430,"closest":{"id":430,"name":"АШАН","point":[37.72297,55.58568],"address":"142715, Московская обл., Ленинский р-н, пос. Совхоз Имени Ленина 24 км. МКАД, влд. 1, АШАН"},"distance":10.8},"title":"СНТ Педагог в 30.34 км от Москвы, вблизи города Домодедово."}