{"name":"Тимошкино","type":"КП","point":[37.102245,55.77155],"site":null,"car":{"distance":49,"time":{"h":0,"m":57}},"developer":"M9 Land","class":"эконом","price":{"from":3400000,"to":5900000},"address":{"name":"Московская обл, Красногорский р-н, Тимошкино д"},"description":"Коттеджный посёлок эконом-класса Тимошкино возводится в Красногорском районе Московской области недалеко от деревни Тимошкино, в 25 километрах от МКАД по Ильинскому шоссе. Застройщиком проекта выступила компания «M9 Land». Коттеджи и участки Посёлок размежеван на 160 участков площадью от 7.24 до 12.68 соток. Покупателям предлагаются земельные участки без подряда назначением под дачное строительство. Цены на предложения в КП Тимошкино начинаются от 3 388 320 руб. за участок. Как купить Всю актуальную информацию о покупке земельных участков в коттеджном посёлке Тимошкино можно узнать связавшись со специалистом застройщика по указанному на этой странице номеру телефона.","readyDate":2017,"id":3605,"railroad":{"closest":{"id":5901,"name":"Усово","patchId":580,"routeId":10,"time":{"h":0,"m":39},"distance":28.21,"count":11,"typeId":null,"nextId":[],"prevId":[5891],"trains":null,"point":[37.2087046,55.7291393],"route":"Смоленское направление"},"distance":8.16},"city":{"closest":{"id":11,"name":"Дедовск","area":"Истра","point":[37.1206,55.8598]},"distance":9.88},"moscow":{"distance":32.37},"medic":{"closest":{"name":"Нахабинская подстанция скорой медицинской помощи","address":"Московская область, Красногорский район, пгт Нахабино, ул. Панфилова, д. 21","pid":"126","id":"9790","metro_name":null,"metro_color":null,"rayon_name":"Красногорский","icon":"/upload/image/icons/med_pom.png","sname":"Станции скорой помощи","point":[37.176518,55.836534]},"distance":8.59},"eco":{"closest":{"point":[36.8891072,55.7497089],"geom":[55.7497089,36.8891072,55.7512546,36.8902123,55.7510373,36.8930876,55.7496832,36.895802,55.7486325,36.8925726],"type":7,"name":"Полигон ТБО Супонево","address":"Одинцовский район","description":"Закрыт в 2000 г.","props":[4,20],"id":268},"distance":13.55}}