{"name":"Соловушка","type":"СНТ","point":[38.148937,55.931781],"site":"","car":{"distance":45,"time":{"h":0,"m":53}},"developer":"","class":"","price":{"from":"","to":""},"address":{"name":""},"description":"Дачный посёлок «Соловушка» расположен в 39 км от центра Москвы, в северо-восточном направлении. В 7 км от поселка находится город Фрязино. Дачный посёлок расположен в экологически чистом районе подмосковья. На машине, без учета пробок, до поселка можно добраться за 53 мин. Благодоря хорошей транспортной доступности поселок подойдет людям планирующим проживать в пригороде и работать в Москве.","readyDate":"","id":3400,"props":{"energy":"","water":"","drainage":"","gas":"","scurity":""},"nature":{"forest":"","water":""},"eco":{"closestId":87,"closest":{"point":[38.053036,55.927086],"type":11,"name":"ОАО «Щелковское рудоуправление»","address":"Щелково","description":"Производство минерального порошка для изготовления асфальтобетона","id":87},"distance":6},"railroad":{"closestId":581,"closest":{"id":581,"name":"Чкаловская","time":{"h":1,"m":2},"distance":38,"count":19,"nextId":[591],"prevId":[571],"point":[38.06311,55.897155],"route":"Ярославское направление","path":{"id":58,"points":[[38.036259,55.906325],[38.06311,55.897155]],"time":{"hours":0,"min":1},"distance":1.96},"type":"станция"},"distance":6.59},"moscow":{"distance":38.73},"city":{"closestId":64,"closest":{"id":64,"point":[38.0523,55.9579],"name":"Фрязино"},"distance":6.68},"medic":{"closestId":9155,"closest":{"id":"9155","name":"Подстанция скорой медицинской помощи п. Биокомбината","point":[38.115855699812755,55.9173026733695],"address":"МО, Щелковский р-н, пос. Биокомбината (здание больницы)","city":"Щелковский"},"distance":2.62},"markets":{"closestId":11793,"closest":{"id":11793,"name":"Азбука Вкуса","point":[37.867866,55.920457],"address":"Московская область, Королёв, проспект Космонавтов, 4В"},"distance":17.55}}