{"name":"Красково","type":"ПСК","point":[37.971667,55.641514],"site":"","car":{"distance":31,"time":{"h":0,"m":50}},"developer":"","class":"","price":{"from":"","to":""},"address":{"name":""},"description":"Дачный посёлок «Красково» расположен в 25 км от центра Москвы, в юго-восточном направлении. В 6 км от поселка находится город Люберцы. Дачный посёлок «Красково» расположен в районе с хорошей экологией. На машине, без учета пробок, до поселка можно добраться за 50 мин. В пешой доступности находится ж/д станция пригородной электички Красково (Казанское направление). На электричке до Москвы 15 остановок, время в пути 48 мин. Поезд прибывает на Казанский вокзал. Благодоря хорошей транспортной доступности поселок подойдет людям планирующим проживать в пригороде и работать в Москве.","readyDate":"","id":1584,"props":{"energy":"","water":"","drainage":"","gas":"","scurity":""},"nature":{"forest":"","water":""},"eco":{"closestId":289,"closest":{"point":[37.9657245,55.6752493],"type":7,"name":"Полигон ТБО Машково","address":"Люберецкий район","description":"Закрыт в 2011 г.","id":289},"distance":3.77},"railroad":{"closestId":811,"closest":{"id":811,"name":"Красково","time":{"h":0,"m":48},"distance":26.97,"count":15,"nextId":[821],"prevId":[801],"point":[37.9828008,55.6497754],"route":"Казанское направление","path":{"id":81,"points":[[37.9537423,55.6554055],[37.9828008,55.6497754]],"time":{"hours":0,"min":1},"distance":1.93},"type":"платформа"},"distance":1.15},"moscow":{"distance":25.28},"city":{"closestId":40,"closest":{"id":40,"point":[37.8935,55.6788],"name":"Люберцы"},"distance":6.42},"medic":{"closestId":8234,"closest":{"id":"8234","name":"Подстанция скорой медицинской помощи Малаховка","point":[38.002644,55.644399],"address":"МО, Люберецкий р-н, п. Малаховка, ул. Комсомольская, 7А","city":"Люберецкий"},"distance":1.97},"markets":{"closestId":4026,"closest":{"id":4026,"name":"Магазины Магнит","point":[37.927537,55.683361],"address":"г, Вольская 1-я ул, 22"},"distance":5.41},"title":"ПСК Красково в 25.28 км от Москвы, вблизи города Люберцы."}