{"name":"Лимберова гора","type":"КП","point":[37.37412,54.734207],"site":null,"car":{"distance":120,"time":{"h":1,"m":36}},"developer":null,"class":null,"price":{"from":null,"to":null},"address":{"name":null},"description":"Коттеджный посёлок «Лимберова гора» расположен в 114 км от Москвы, в северо-западном направлении. Коттеджный посёлок расположен в экологически чистом районе подмосковья. На машине, без учета пробок, до поселка можно добраться за 1 час 36 мин. В пешой доступности находится ж/д станция пригородной электички Тарусская (Курское направление). На электричке до Москвы 35 остановок, время в пути 2 час 37 мин. Поезд прибывает на Курский вокзал.","readyDate":null,"id":1862,"railroad":{"closest":{"id":4761,"name":"Тарусская","patchId":467,"routeId":8,"time":{"h":2,"m":37},"distance":123.02,"count":35,"typeId":3,"nextId":[4771],"prevId":[4751],"trains":null,"point":[37.400894165039055,54.735052876490194],"route":"Курское направление"},"distance":1.72},"city":{"closest":{"id":51,"name":"Протвино","area":"Протвино","point":[37.2183,54.8706]},"distance":18.16},"moscow":{"distance":114.14},"medic":{"closest":{"name":"Отделение скорой медицинской помощи Больницы Пущинского научного центра Российской Академии наук","address":"142290, Московская область, г. Пущино, ул. Институтская, д.1","pid":"126","id":"10966","metro_name":null,"metro_color":null,"rayon_name":"Балашиха","icon":"/upload/image/icons/med_pom.png","sname":"Станции скорой помощи","point":[37.60357415344178,54.83019984976472]},"distance":18.18},"eco":{"closest":{"point":[37.21005,54.86605],"type":2,"name":"Институт физики высоких энергий","address":"Протвино","description":"На территории действует комплекс ускорителей заряженных частиц","id":50},"distance":18.04}}