{"name":"Елки","type":"КП","point":[37.30208,55.998648],"site":null,"car":{"distance":46,"time":{"h":0,"m":44}},"developer":null,"class":null,"price":{"from":null,"to":null},"address":{"name":null},"description":"Коттеджный посёлок «Елки» находится в 34 км от Москвы, в северо-западном направлении. Коттеджный посёлок расположен в экологически чистом районе подмосковья. На машине, без учета пробок, до поселка можно добраться за 44 мин. Благодоря хорошей транспортной доступности поселок подойдет людям планирующим проживать в пригороде и работать в Москве.","readyDate":null,"id":988,"railroad":{"closest":{"id":2801,"name":"Фирсановская","patchId":275,"routeId":4,"time":{"h":0,"m":50},"distance":32.97,"count":13,"typeId":2,"nextId":[2811],"prevId":[2791],"trains":130,"point":[37.251006,55.960402],"route":"Ленинградское направление"},"distance":5.31},"market":{"closest":{"id":11581,"address":"Москва, Зеленоград, к514с1","name":"Азбука Вкуса","city":"Москва","date_review":"11/1/2019","holding_name":"Азбука Вкуса","website":"","working_time":"00:00-24:00","lon":37.236738,"lat":55.99755},"distance":4.06},"city":{"closest":{"id":36,"name":"Лобня","area":"Лобня","point":[37.4751,56.0121]},"distance":10.86},"moscow":{"distance":33.85},"medic":{"closest":{"name":"Подстанция скорой медицинской помощи Сходня","address":"141420, Московская область, г. Химки, мкр. Сходня, ул.Мичурина, дом 31А","pid":"126","id":"10947","metro_name":null,"metro_color":null,"rayon_name":"Балашиха","icon":"/upload/image/icons/med_pom.png","sname":"Станции скорой помощи","point":[37.300826,55.94321]},"distance":6.16},"eco":{"closest":{"point":[37.254843,55.979007],"type":5,"name":"Очистные сооружения Зеленограда","address":"Савёлки","description":"Мосводоканал","id":236},"distance":3.66}}