{"name":"Сосновка-2","type":"СНТ","point":[38.634405,55.810811],"site":null,"car":{"distance":81,"time":{"h":1,"m":33}},"developer":null,"class":null,"price":{"from":null,"to":null},"address":{"name":null},"description":null,"readyDate":null,"id":3422,"railroad":{"closest":{"id":2311,"name":"Вохна","patchId":229,"routeId":3,"time":{"h":1,"m":31},"distance":64.32,"count":22,"typeId":2,"nextId":[2321],"prevId":[2301],"trains":null,"point":[38.630572,55.769461],"route":"Горьковское направление"},"distance":4.6},"city":{"closest":{"id":48,"name":"Павловский Посад","area":"Павловский Посад","point":[38.6513,55.7794]},"distance":3.65},"moscow":{"distance":63.87},"medic":{"closest":{"name":"Отделение скорой медицинской помощи Павлово-Посадской ЦРБ","address":"МО, г. Павловский Посад, ул. Фрунзе, д. 28А","pid":"126","id":"10553","metro_name":null,"metro_color":null,"rayon_name":"Павлово-Посадский","icon":"/upload/image/icons/med_pom.png","sname":"Станции скорой помощи","point":[38.660013,55.771064]},"distance":4.7},"eco":{"closest":{"point":[38.659167,55.775833],"type":4,"name":"ТЭЦ-30","address":"Павловский Посад","description":"Входит в состав ГРЭС-3, Мосэнерго","id":223},"distance":4.19}}