{"name":"Green Village","type":"КП","point":[37.701441,56.265009],"site":null,"car":{"distance":76,"time":{"h":1,"m":21}},"developer":null,"class":null,"price":{"from":null,"to":null},"address":{"name":null},"description":"Коттеджный посёлок «Green Village» расположен в 57 км от Москвы, в северо-восточном направлении. Коттеджный посёлок расположен в экологически чистом районе подмосковья. На машине, без учета пробок, до поселка можно добраться за 1 час 21 мин.","readyDate":null,"id":4134,"railroad":{"closest":{"id":5091,"name":"Турист","patchId":499,"routeId":9,"time":{"h":1,"m":20},"distance":53.23,"count":21,"typeId":2,"nextId":[5101],"prevId":[5081],"trains":null,"point":[37.5124527,56.243512],"route":"Савёловское направление"},"distance":11.92},"market":{"closest":{"id":11788,"address":"Московская область, Дмитровский городской округ, Дмитров, Профессиональная улица, 7","name":"Азбука Вкуса","city":"Москва","date_review":"11/1/2019","holding_name":"Азбука Вкуса","website":"","working_time":"00:00-24:00","lon":37.520913,"lat":56.352547},"distance":14.79},"city":{"closest":{"id":74,"name":"Яхрома","area":"Дмитровский","point":[37.4832,56.2891]},"distance":13.74},"moscow":{"distance":57.36},"medic":{"closest":{"name":"Яхромская подстанция скорой медицинской помощи","address":"Московская обл., Дмитровский р-он, г. Яхрома, ул. Ленина, д. 5","pid":"126","id":"10155","metro_name":null,"metro_color":null,"rayon_name":"Дмитровский","icon":"/upload/image/icons/med_pom.png","sname":"Станции скорой помощи","point":[37.485152,56.286697]},"distance":13.57},"eco":{"closest":{"point":[37.520986,56.397644],"type":8,"name":"Илим Гофра, филиал в Дмитрове","address":"Дмитров","description":"Группа «Илим»","id":307},"distance":18.47}}