{"name":"Репка","type":"СНТ","point":[36.942621,55.62587],"site":null,"car":{"distance":54,"time":{"h":0,"m":48}},"developer":null,"class":null,"price":{"from":null,"to":null},"address":{"name":null},"description":null,"readyDate":null,"id":2990,"railroad":{"closest":{"id":5481,"name":"Голицыно","patchId":538,"routeId":10,"time":{"h":1,"m":9},"distance":43.41,"count":19,"typeId":null,"nextId":[2631,5491,5911],"prevId":[5471],"trains":null,"point":[36.9872903,55.61572]},"distance":3.02},"city":{"closest":{"id":10,"name":"Голицыно","area":"Одинцовский","point":[36.9856,55.619]},"distance":2.8},"moscow":{"distance":44.59},"medic":{"closest":{"name":"Голицинская подстанция скорой медицинской помощи","address":"Московская область, Одинцовский район, р.п. Большие Вяземы, ул. Институт, стр. 9/1","pid":"126","id":"9968","metro_name":null,"metro_color":null,"rayon_name":"Одинцовский","icon":"/upload/image/icons/med_pom.png","sname":"Станции скорой помощи","point":[36.997367,55.626985]},"distance":3.44},"eco":{"closest":{"point":[36.9110477,55.6205571],"geom":[55.6205571,36.9110477,55.621396,36.907363,55.6223019,36.9051898,55.6234165,36.9049108,55.624204,36.9084996,55.6239011,36.9088,55.6240617,36.9093177,55.6249037,36.9099131,55.624834,36.9106333,55.6251081,36.9110785,55.6249234,36.9114219,55.6241919,36.9115412,55.622851,36.9129,55.621971,36.913277,55.6207389,36.9132578],"type":7,"name":"Полигон ТБО Часцы","address":"Одинцовский район","description":"Закрыт в 2014 г., незаконно принимал отходы, горел в 2018 г.","props":[4,20],"id":255},"distance":2.07}}