{"name":"Озеро жемчужин","type":"КП","point":[36.323199,56.202316],"site":"","car":{"distance":130,"time":{"h":1,"m":55}},"developer":"Своя дача","class":"комфорт","price":{"from":"","to":""},"address":{"name":"Московская обл, Клинский р-н, Тархово д"},"description":"Коттеджный посёлок «Озеро жемчужин» находится в 95 км от центра Москвы, в северо-западном направлении. Коттеджный посёлок «Озеро жемчужин» расположен в районе с хорошей экологией. На машине, без учета пробок, до поселка можно добраться за 1 час 55 мин.","readyDate":2016,"id":2478,"props":{"energy":"","water":"","drainage":"","gas":"","scurity":""},"nature":{"forest":"","water":""},"eco":{"closestId":95,"closest":{"point":[36.6855383,56.3291968],"type":8,"name":"Термоприбор","address":"Клин","description":"Производство ртутных термометров","id":95},"distance":26.45},"railroad":{"closestId":4311,"closest":{"id":4311,"name":"Лесодолгоруково","time":{"h":2,"m":12},"distance":94.98,"count":32,"nextId":[4321],"prevId":[4301],"point":[36.3454541,56.01056],"route":"Рижское направление","path":{"id":423,"points":[[36.410925686359406,55.99134411938637],[36.40774726867676,55.99295680952515],[36.40362739562988,55.99415690736177],[36.39504432678223,55.99650899104543],[36.38663291931152,55.99871693935745],[36.37796401977539,56.000732782007965],[36.37350082397461,56.001404706192226],[36.36955261230469,56.00279651198113],[36.36277198791504,56.006155836666984],[36.35916709899902,56.00788337564109],[36.3552188873291,56.0094189009949],[36.3454541,56.01056]],"time":{"hours":0,"min":3},"distance":4.67},"type":"платформа"},"distance":21.37},"moscow":{"distance":94.91},"city":{"closestId":9,"closest":{"id":9,"point":[36.552,56.3202],"name":"Высоковск"},"distance":19.27},"medic":{"closestId":9375,"closest":{"id":"9375","name":"Высоковская подстанция скорой медицинской помощи","point":[36.555512,56.322424],"address":"141650, Московская область, Клинский р-н, г.Высоковск, ул. Владыкина, 24А","city":"Клинский"},"distance":19.6},"markets":{"closestId":6553,"closest":{"id":6553,"name":"SPAR","point":[37.160073,55.984506],"address":"Зеленоград, кор.1456"},"distance":57.28},"title":"КП Озеро жемчужин в 94.91 км от Москвы, вблизи города Высоковск."}