{"name":"ФСБ Пехорка","type":"ДП","point":[37.98337,55.629079],"site":"","car":{"distance":31,"time":{"h":0,"m":50}},"developer":"","class":"","price":{"from":"","to":""},"address":{"name":""},"description":"Дачный посёлок «ФСБ Пехорка» расположен в 27 км от центра Москвы, в юго-восточном направлении. В 8 км от поселка находится город Лыткарино. Дачный посёлок расположен в экологически чистом районе подмосковья. На машине, без учета пробок, до поселка можно добраться за 50 мин. В пешой доступности находится ж/д станция пригородной электички Красково (Казанское направление). На электричке до Москвы 15 остановок, время в пути 48 мин. Поезд прибывает на Казанский вокзал. Благодоря хорошей транспортной доступности поселок подойдет людям планирующим проживать в пригороде и работать в Москве.","readyDate":"","id":3823,"props":{"energy":"","water":"","drainage":"","gas":"","scurity":""},"nature":{"forest":"","water":""},"eco":{"closestId":289,"closest":{"point":[37.9657245,55.6752493],"type":7,"name":"Полигон ТБО Машково","address":"Люберецкий район","description":"Закрыт в 2011 г.","id":289},"distance":5.25},"railroad":{"closestId":811,"closest":{"id":811,"name":"Красково","time":{"h":0,"m":48},"distance":26.97,"count":15,"nextId":[821],"prevId":[801],"point":[37.9828008,55.6497754],"route":"Казанское направление","path":{"id":81,"points":[[37.9537423,55.6554055],[37.9828008,55.6497754]],"time":{"hours":0,"min":1},"distance":1.93},"type":"платформа"},"distance":2.3},"moscow":{"distance":26.6},"city":{"closestId":39,"closest":{"id":39,"point":[37.9034,55.5779],"name":"Лыткарино"},"distance":7.59},"medic":{"closestId":8235,"closest":{"id":"8235","name":"Подстанция скорой медицинской помощи Октябрьский","point":[37.972649,55.613687],"address":"МО, Люберецкий р-н, п. Октябрьский, ул. Ленина, 48","city":"Люберецкий"},"distance":1.84},"markets":{"closestId":11789,"closest":{"id":11789,"name":"Азбука Вкуса","point":[38.07395,55.605677],"address":"Московская область, Жуковский, улица Баженова, 11"},"distance":6.25}}