{"name":"Родник","type":"СНТ","point":[37.402561,55.998245],"site":"","car":{"distance":44,"time":{"h":0,"m":47}},"developer":"","class":"","price":{"from":"","to":""},"address":{"name":""},"description":"Дачный посёлок «Родник» находится в 31 км от центра Москвы, в северо-западном направлении. В 5 км от поселка находится город Лобня. На машине, без учета пробок, до поселка можно добраться за 47 мин. Благодоря хорошей транспортной доступности поселок подойдет людям планирующим проживать в пригороде и работать в Москве.","readyDate":"","id":3020,"props":{"energy":"","water":"","drainage":"","gas":"","scurity":""},"nature":{"forest":"","water":""},"eco":{"closestId":300,"closest":{"point":[37.375145,55.997709],"type":7,"name":"Полигон ТБО Шемякино (незаконный)","address":"Химки","description":"Действовал в 2008-2010 гг.","id":300},"distance":1.71},"railroad":{"closestId":5011,"closest":{"id":5011,"name":"Лобня","time":{"h":0,"m":44},"distance":26.05,"count":13,"nextId":[4471,5021,5991],"prevId":[5001],"point":[37.48487949371338,56.01354532298036],"route":"Савёловское направление","path":{"id":491,"points":[[37.4986609,55.9838866],[37.49187469482422,55.99823696132359],[37.48487949371338,56.01354532298036]],"time":{"hours":0,"min":3},"distance":3.41}},"distance":5.39},"moscow":{"distance":30.59},"city":{"closestId":36,"closest":{"id":36,"point":[37.4751,56.0121],"name":"Лобня"},"distance":4.77},"medic":{"closestId":10229,"closest":{"id":"10229","name":"Станция скорой медицинской помощи г. Лобня","point":[37.45971123809789,56.0157476181405],"address":"МО, Лобня, мкр. Букино, ул. Заречная, д.15","city":"Балашиха"},"distance":4.05},"markets":{"closestId":11787,"closest":{"id":11787,"name":"Азбука Вкуса","point":[37.53082,56.056088],"address":"Московская область, городской округ Мытищи, деревня Шолохово, Дмитровское шоссе, 2Бс1"},"distance":10.24}}